markoff
tests
