Metadata-Version: 1.1
Name: markoff
Version: 0.1.1
Summary: A simple phrase generating class using Markov chains
Home-page: https://github.com/kneitinger/markoff
Author: Kyle J. Kneitinger
Author-email: kneit@pdx.edu
License: BSD
Platform: UNKNOWN
Classifier: Development Status :: 3 - Alpha
Classifier: Environment :: Console
Classifier: Intended Audience :: Developers
Classifier: License :: OSI Approved :: BSD License
Classifier: Natural Language :: English
Classifier: Operating System :: OS Independent
Classifier: Topic :: Text Processing :: Linguistic
